euler/__init__.py
euler/angles.py
euler/convert.py
euler/matrix.py
euler/py.typed
euler/su2.py
euler/utils.py
euler-1.0.3.dist-info/METADATA
euler-1.0.3.dist-info/WHEEL
euler-1.0.3.dist-info/licenses/LICENSE
euler-1.0.3.dist-info/RECORD
