Metadata-Version: 2.3
Name: euler
Version: 1.0.3
Summary: A library for Euler angle computation and conversion.
Project-URL: Repository, https://github.com/neverlocal/euler
Project-URL: Issues, https://github.com/neverlocal/euler/issues
Author: NeverLocal
License: LGPL-3.0
Classifier: Development Status :: 4 - Beta
Classifier: Natural Language :: English
Classifier: Operating System :: OS Independent
Classifier: Programming Language :: Python :: 3
Classifier: Programming Language :: Python :: 3.10
Classifier: Programming Language :: Python :: 3.11
Classifier: Programming Language :: Python :: 3.12
Classifier: Programming Language :: Python :: 3.13
Classifier: Typing :: Typed
Requires-Python: >=3.10
Requires-Dist: numpy>=1.23
